pyrin_network-0.1.9.dist-info/METADATA
pyrin_network-0.1.9.dist-info/WHEEL
pyrin.libs/libcrypto-a50d99cb.so.3
pyrin.libs/libssl-91d34894.so.3
pyrin/uint256.py
pyrin/xoshiro256plusplus.py
pyrin/__init__.py
pyrin/pyrin.cpython-310-x86_64-linux-gnu.so
pyrin_network-0.1.9.dist-info/RECORD
