Metadata-Version: 2.3
Name: pyrin-network
Version: 0.1.9
Classifier: Programming Language :: Rust
Classifier: Programming Language :: Python :: Implementation :: CPython
Classifier: Programming Language :: Python :: Implementation :: PyPy
Requires-Dist: pytest ; extra == 'tests'
Provides-Extra: tests
Summary: Pyrin SDK for the ecosystem
Keywords: pyrin,pyrin network
Requires-Python: >=3.8
Project-URL: Homepage, https://github.com/Pyrinpyi/pyrin/tree/master/sdk/python
Project-URL: Issues, https://github.com/Pyrinpyi/pyrin/issues
